{
  "target": "github.com",
  "type": "Domain",
  "threat_score": 0,
  "context_score": 5,
  "osint_score": 0,
  "feeds": {
    "meta": {
      "target": "github.com"
    },
    "WHOIS": {
      "registrar": "MarkMonitor, Inc.",
      "org": "GitHub, Inc.",
      "creation_date": "2007-10-09 18:20:50",
      "expiration_date": "2026-10-09 18:20:50",
      "country": "US"
    },
    "SSL": [],
    "PassiveDNS": {
      "records": [
        {
          "address": "140.82.113.25",
          "first": "2025-07-20T19:32:01",
          "last": "2025-07-20T19:59:48",
          "hostname": "lb-140-82-113-25-iad.github.com",
          "record_type": "A",
          "indicator_link": "/indicator/hostname/lb-140-82-113-25-iad.github.com",
          "flag_url": "assets/images/flags/us.png",
          "flag_title": "United States",
          "asset_type": "hostname",
          "asn": "AS36459 github  inc."
        },
        {
          "address": "140.82.114.25",
          "first": "2025-07-19T15:37:24",
          "last": "2025-07-19T16:06:31",
          "hostname": "lb-140-82-114-25-iad.github.com",
          "record_type": "A",
          "indicator_link": "/indicator/hostname/lb-140-82-114-25-iad.github.com",
          "flag_url": "assets/images/flags/us.png",
          "flag_title": "United States",
          "asset_type": "hostname",
          "asn": "AS36459 github  inc."
        },
        {
          "address": "140.82.112.26",
          "first": "2025-07-19T13:51:30",
          "last": "2025-07-19T14:30:06",
          "hostname": "lb-140-82-112-26-iad.github.com",
          "record_type": "A",
          "indicator_link": "/indicator/hostname/lb-140-82-112-26-iad.github.com",
          "flag_url": "assets/images/flags/us.png",
          "flag_title": "United States",
          "asset_type": "hostname",
          "asn": "AS36459 github  inc."
        },
        {
          "address": "140.82.116.33",
          "first": "2025-07-16T19:55:03",
          "last": "2025-07-16T20:37:18",
          "hostname": "www.npm.pkg.github.com",
          "record_type": "A",
          "indicator_link": "/indicator/hostname/www.npm.pkg.github.com",
          "flag_url": "assets/images/flags/us.png",
          "flag_title": "United States",
          "asset_type": "hostname",
          "asn": "AS36459 github  inc."
        },
        {
          "address": "pkg.github.com",
          "first": "2025-07-16T11:35:44",
          "last": "2025-07-16T11:35:46",
          "hostname": "www.npm.pkg.github.com",
          "record_type": "CNAME",
          "indicator_link": "/indicator/hostname/www.npm.pkg.github.com",
          "flag_url": "assets/images/flags/us.png",
          "flag_title": "United States",
          "asset_type": "hostname",
          "asn": "AS36459 github  inc."
        }
      ]
    },
    "CampaignTags": [],
    "WalletTags": [],
    "Web3": {},
    "OSINT_SCORE": 0,
    "OSINT_TAGS": []
  },
  "tags": [
    "KNOWN_GOOD",
    "passive-dns-present"
  ],
  "label": "KNOWN_GOOD"
}